setup.py
vis_analysis_torch/__init__.py
vis_analysis_torch/bbox_visualization.py
vis_analysis_torch/common_visualization.py
vis_analysis_torch/pose_visualization.py
vis_analysis_torch/results_analysis.py
vis_analysis_torch/utils.py
vis_analysis_torch.egg-info/PKG-INFO
vis_analysis_torch.egg-info/SOURCES.txt
vis_analysis_torch.egg-info/dependency_links.txt
vis_analysis_torch.egg-info/requires.txt
vis_analysis_torch.egg-info/top_level.txt